condox/__init__.py
condox/config.py
condox/util.py
condox/trans/__init__.py
condox/trans/fragment.py
condox/trans/html2docx.py
condox/trans/legacy.py
condox/trans/util.py
condox/trans/html2latex/__init__.py
condox/trans/html2latex/converter.py
condox/trans/html2latex/header.py
condox/trans/html2latex/rules.py
condox/trans/html2latex/util.py
condox-0.1.1.dist-info/LICENSE
condox-0.1.1.dist-info/METADATA
condox-0.1.1.dist-info/WHEEL
condox-0.1.1.dist-info/top_level.txt
condox-0.1.1.dist-info/RECORD
